sheldon
sheldon_cli
