Metadata-Version: 1.0
Name: sheldon
Version: 0.0.4
Summary: Perfect chat bot for your team
Home-page: https://github.com/sevazhidkov/sheldon
Author: sevazhidkov
Author-email: zhidkovseva@gmail.com
License:  The MIT License (MIT)
Platform: UNKNOWN
